README.md
pyproject.toml
setup.py
ThorlabsPM100/ThorlabsPM100.py
ThorlabsPM100/VISA_wrapper_metaclass.py
ThorlabsPM100/__init__.py
ThorlabsPM100/usbtmc.py
ThorlabsPM100.egg-info/PKG-INFO
ThorlabsPM100.egg-info/SOURCES.txt
ThorlabsPM100.egg-info/dependency_links.txt
ThorlabsPM100.egg-info/top_level.txt