Metadata-Version: 2.1
Name: ThorlabsPM100
Version: 1.2.3
Summary: Interface to the PM100A/D power meter from Thorlabs.
Home-page: http://pythonhosted.org/ThorlabsPM100
Author: Pierre CladÃ©
Author-email: pierre.clade@spectro.jussieu.fr
Maintainer: Pierre CladÃ©
Maintainer-email: pierre.clade@spectro.jussieu.fr
License: This software can be used under one of the following two licenses: (1) The BSD license. (2) Any other license, as long as it is obtained from the original author.
Keywords: Thorlabs,PM100,PM100A,PM100D
Classifier: Development Status :: 4 - Beta
Classifier: Intended Audience :: Education
Classifier: Intended Audience :: Science/Research
Classifier: License :: OSI Approved :: BSD License
Classifier: Programming Language :: Python
Classifier: Topic :: Scientific/Engineering
Classifier: Topic :: Scientific/Engineering :: Physics
Classifier: Topic :: Software Development
Classifier: Topic :: Software Development :: Libraries
Classifier: Topic :: Software Development :: Libraries :: Python Modules
